{
	"configurations" : 
	[
		{
			"directories" : 
			[
				{
					"build" : ".",
					"minimumCMakeVersion" : 
					{
						"string" : "3.14"
					},
					"projectIndex" : 0,
					"source" : ".",
					"targetIndexes" : 
					[
						0
					]
				}
			],
			"name" : "Debug",
			"projects" : 
			[
				{
					"directoryIndexes" : 
					[
						0
					],
					"name" : "SWA",
					"targetIndexes" : 
					[
						0
					]
				}
			],
			"targets" : 
			[
				{
					"directoryIndex" : 0,
					"id" : "SWA::@6890427a1f51a3e7e1df",
					"jsonFile" : "target-SWA-Debug-6fe656d7c0ea55d8457f.json",
					"name" : "SWA",
					"projectIndex" : 0
				}
			]
		}
	],
	"kind" : "codemodel",
	"paths" : 
	{
		"build" : "C:/Users/Gebruiker/Source/Repos/SWA/out/build/x64-Debug",
		"source" : "C:/Users/Gebruiker/Source/Repos/SWA"
	},
	"version" : 
	{
		"major" : 2,
		"minor" : 0
	}
}
